pytest2md/__init__.py
pytest2md/mdtool.py
pytest2md/p2m.py
pytest2md/repo_search.py
pytest2md/strutils.py
pytest2md-20200602.dist-info/LICENSE
pytest2md-20200602.dist-info/METADATA
pytest2md-20200602.dist-info/WHEEL
pytest2md-20200602.dist-info/top_level.txt
pytest2md-20200602.dist-info/RECORD
