Metadata-Version: 2.1
Name: pytest2md
Version: 20200602
Summary: Create and run markdown Readmes from within pytest
Home-page: https://github.com/axiros/pytest2md
Author: gk
Author-email: gk@axiros.com
License: BSD
Keywords: markdown,markup,testing,pytest
Platform: UNKNOWN
Classifier: Development Status :: 4 - Beta
Classifier: Intended Audience :: Developers
Classifier: Topic :: Text Processing :: Markup
Classifier: Operating System :: POSIX
Classifier: License :: OSI Approved :: BSD License
Classifier: Programming Language :: Python :: 3
Requires-Dist: ansi2html
